lucytok/__init__.py
lucytok/asciifold.py
lucytok/british_american.py
lucytok/compounds.py
lucytok/plurals.py
lucytok/porter.py
lucytok/tokenizer.py
lucytok-0.1.10.dist-info/LICENSE
lucytok-0.1.10.dist-info/METADATA
lucytok-0.1.10.dist-info/WHEEL
lucytok-0.1.10.dist-info/RECORD
